[
    {
        "cpf": "38630096810",
        "nome": "lele",
        "email": "lele@g.com",
        "senha": "$2b$12$URovuOhlweaGO1u9SZSWXOCIZMpAtMdVA1iAGqQYJf5tdzHEwq1Ui",
        "perfil": "Aluno",
        "palavra_chave": "Lindo"
    },
    {
        "cpf": "94557489596",
        "nome": "admin",
        "email": "admin@g.com",
        "senha": "$2b$12$ylhdSNq0D40u9vN91rLxF.dWSCf6O6aJekkQzMVyLy0goLDvTDrJ.",
        "perfil": "Secretaria"
    },
    {
        "cpf": "12345678900",
        "nome": "dede",
        "email": "dede@gmail.com",
        "senha": "$2b$12$7gRm0dm7452DCCqUe31Ls.zpTKiUeAh4WiLQ7a20pShPcDha2pGJ.",
        "perfil": "Aluno"
    },
    {
        "cpf": "12345678911",
        "nome": "admin",
        "email": "admin@g.com",
        "senha": "$2b$12$1eaermySkQc2OGnvl523c.FYjIwoqA4LE9SBFi6GZRf/gYq45lf6K",
        "perfil": "Secretaria"
    },
    {
        "cpf": "11111111111",
        "nome": "lelezorpinho",
        "email": "lele@g.cmo",
        "senha": "$2b$12$FCrYnIv08JStsac1XN63De228fX8oSocXqO.iNvrfHLqnllE9xJle",
        "perfil": "Aluno"
    },
    {
        "cpf": "88888888888",
        "nome": "adminzin",
        "email": "lele@g.com",
        "senha": "$2b$12$yzKOEXGli88mHkBHhYMqR.8.r0gMnJlJruFcjN/E/iLp1dHxqSM3W",
        "perfil": "Secretaria"
    },
    {
        "cpf": "94557489591",
        "nome": "superADM",
        "email": "adm@g.com",
        "senha": "$2b$12$2JzP3XacF/3IAqB0nglCxO75/IFOnhJifm9EJCGhKp.yjOUCSvAne",
        "perfil": "Secretaria",
        "palavra_chave": "TESTE"
    },
    {
        "cpf": "45557489591",
        "nome": "Jorge ben Jor",
        "email": "jorge@gmail.com",
        "senha": "$2b$12$hZNlYoLyj369mAqVUHsozeeRPlHDIPF1QpXLoImFbT.ie6m5piQa.",
        "perfil": "Aluno"
    },
    {
        "cpf": "38630096814",
        "nome": "Borges",
        "email": "Borges@gmail.com",
        "senha": "$2b$12$HZt0G.pYNso0Qh4JNzypAusPr/6kJ6DAuhpyUaZn8g0PJTfdgnzES",
        "perfil": "Secretaria"
    },
    {
        "cpf": "38630096812",
        "nome": "Porto",
        "email": "porto@g.com",
        "senha": "$2b$12$9Y/FcWvVnCCBq89M.EJQ5uM1C93iO0tHJ5/a5hDk/Murs51TKNBny",
        "perfil": "Aluno",
        "palavra_chave": "VIDA"
    },
    {
        "cpf": "38630096850",
        "nome": "Thomaz",
        "email": "thomaz@gmail.com",
        "senha": "$2b$12$m5/G5QAVoazTguAesmYvbeTKCW0yvGqJd3sCzz0yAG0GCHlQrmBEy",
        "perfil": "Aluno",
        "palavra_chave": "Vida"
    },
    {
        "cpf": "38630096916",
        "nome": "Leandro",
        "email": "Leandro@gmail.com",
        "senha": "$2b$12$CfI3qvnSXAdXCTnsM9DFN.UiRf0YzeIv7RxEAZfED.AHnjbhL1wqG",
        "perfil": "Aluno",
        "palavra_chave": "Dica"
    },
    {
        "cpf": "38630096817",
        "nome": "Leandro Sillva",
        "email": "Leandro@gmial.com",
        "senha": "$2b$12$qGan/5pWr9X0Yh44jxJDmee0tRb5w/lBo51tbdjruipmgXq9eVQw6",
        "perfil": "Aluno",
        "palavra_chave": "Dica"
    },
    {
        "cpf": "94557489590",
        "nome": "admPP",
        "email": "adm@gmail.com",
        "senha": "$2b$12$OYgGSCCIQRTa8NOnHozndujzfOxYXdiap6NkaK.KVzhkWEjZoZiEm",
        "perfil": "Secretaria",
        "palavra_chave": "Dica"
    },
    {
        "cpf": "38630096822",
        "nome": "Leandro",
        "email": "Leandro@gmai.com",
        "senha": "$2b$12$NLRyTYnpVVcdIZkBErbsN.qSVp4t95UYmiuQH5Bvx6Q4qutKQA2/K",
        "perfil": "Aluno",
        "palavra_chave": "Dica"
    },
    {
        "cpf": "38630096899",
        "nome": "Leandro",
        "email": "Leandro@gmail.com",
        "senha": "$2b$12$xjpuaVWrVl/7LsZTi4/ToO3m8sny.aD/YYdB5NnTvG4wpb/lJ53R.",
        "perfil": "Aluno",
        "palavra_chave": "Dica"
    },
    {
        "cpf": "94557489592",
        "nome": "admTeste",
        "email": "adm@gmail.com",
        "senha": "$2b$12$PNXlZS38izXPZZaZ9X0oTOVD2.TomKRjfI/AvuWg6ZhIJdOiV8/Ia",
        "perfil": "Secretaria",
        "palavra_chave": "Dica"
    },
    {
        "cpf": "38630096877",
        "nome": "Pedro",
        "email": "Pedro@gmail.com",
        "senha": "$2b$12$vD6xEpoMwaSBpyMEI9PlIeFhqUIOohIovFIYYkBinbk0s1oThOMoa",
        "perfil": "Aluno",
        "palavra_chave": "Dica"
    },
    {
        "cpf": "38630096855",
        "nome": "Leandrooo",
        "email": "Leandro@gamil.com",
        "senha": "$2b$12$Z5DTr2FcUlOJdLrf.CDcguBwbkBED8gmgCjiQ957koZ3JEQryXJhC",
        "perfil": "Aluno",
        "palavra_chave": "Dica"
    },
    {
        "cpf": "94557489500",
        "nome": "admTeste",
        "email": "admteste@gmail.com",
        "senha": "$2b$12$ZhPsw2gcpCW/.sjMGt53YuD7bGmAKBO07IbGmXF6STmCXypZaPIrC",
        "perfil": "Secretaria",
        "palavra_chave": "Dica"
    },
    {
        "cpf": "94557489501",
        "nome": "propositalmentecinal",
        "email": "po@g.com",
        "senha": "$2b$12$Ifg3th2wi7p5yNmiyZULTeESQHDCTtZFliKbWElQby0YCgXLB5X1.",
        "perfil": "Secretaria",
        "palavra_chave": "oi ne"
    },
    {
        "cpf": "38630096910",
        "nome": "Prof da Silva",
        "email": "prof@g.com",
        "senha": "$2b$12$FSoCsmWDkAEt6calBdx3D.eVoog9sIKNEruO4V9AaIT8666kl5vD2",
        "perfil": "Professor",
        "palavra_chave": "prof"
    },
    {
        "cpf": "38630096710",
        "nome": "pomba silva",
        "email": "pomba@g.com",
        "senha": "$2b$12$wE0LAph2WN85PO18xDJ5lOQPe9MqCsjEExaW6jbGu.WlRyqgE5/LK",
        "perfil": "Secretaria",
        "palavra_chave": "oi ne"
    },
    {
        "cpf": "38630096610",
        "nome": "teste",
        "email": "pol@g.com",
        "senha": "$2b$12$B5OgHvLRN.XMYoke8ndY7.7hrz7GKoKtoMmnblU/e2Nb86UFASrS6",
        "perfil": "Aluno",
        "palavra_chave": "teste"
    },
    {
        "cpf": "38630096510",
        "nome": "Ambrosio",
        "email": "amb@g.com",
        "senha": "$2b$12$VWo7m1yHxE2sNo0facDbuuRv5Um9Z9sewyugTHrOaeZnqw1tAvw1K",
        "perfil": "Aluno",
        "palavra_chave": "teste"
    },
    {
        "cpf": "38630096410",
        "nome": "Nava",
        "email": "nava@g.com",
        "senha": "$2b$12$ghulrJHmOAsYD8tUmc3tgeaZcvSXuylTwFYOBc5xCORuDm.1Es4Ry",
        "perfil": "Aluno",
        "palavra_chave": "teste"
    },
    {
        "cpf": "38630096310",
        "nome": "Safira",
        "email": "Safi@g.com",
        "senha": "$2b$12$xu0b4pZVf2zF18UX5veUx.umOMaiNbXuAQSyLFBMQnh0ub2RLr/vC",
        "perfil": "Aluno",
        "palavra_chave": "teste"
    },
    {
        "cpf": "38630096210",
        "nome": "Vitoria",
        "email": "vi@g.com",
        "senha": "$2b$12$jfCAyf/AopgxrxMkDuvTu.JnV.8jPT1fV2Zqms9EpWjrd7Cyw.MPO",
        "perfil": "Aluno",
        "palavra_chave": "teste"
    },
    {
        "cpf": "38630096110",
        "nome": "Samuca",
        "email": "samuca@g.com",
        "senha": "$2b$12$NlQEfYw3JiVd67rpIGgyauSWIeV/BCv/LK2W/ykbLJ.Cv3la2HLAm",
        "perfil": "Aluno",
        "palavra_chave": "teste"
    },
    {
        "cpf": "94557489991",
        "nome": "Bruno",
        "email": "Bruno@g.com",
        "senha": "$2b$12$x6GGHc6Twg9i7PzRHQtatux7.P2qE36IbzDsTDwNoI4ILWbUJiKSa",
        "perfil": "Aluno",
        "palavra_chave": "teste"
    },
    {
        "cpf": "94557489891",
        "nome": "Lucas",
        "email": "lucas@g.com",
        "senha": "$2b$12$HjIhd3FVFPjix6nhVOjILeCD//gsuCQhOMUmGwSzLw7C4r5BM6PCe",
        "perfil": "Aluno",
        "palavra_chave": "teste"
    },
    {
        "cpf": "94557489791",
        "nome": "Felipe",
        "email": "f@g.com",
        "senha": "$2b$12$ghwUum/E5KMb34MBIRwsoe2u7RJRWXuYTkzmj8syRuETeY/clRis.",
        "perfil": "Aluno",
        "palavra_chave": "teste"
    },
    {
        "cpf": "94557489593",
        "nome": "Claudio Boghi",
        "email": "professor@gmail.com",
        "senha": "$2b$12$BUqOoqSHb7rOTk4KK/CZzuMlIf9i.Vx9oHqmppMGGR0okeWNV6k/W",
        "perfil": "Professor",
        "palavra_chave": "PIM"
    }
]